retrotx/__init__.py
retrotx-0.0.1a1.dist-info/licenses/LICENSE
retrotx-0.0.1a1.dist-info/METADATA
retrotx-0.0.1a1.dist-info/WHEEL
retrotx-0.0.1a1.dist-info/top_level.txt
retrotx-0.0.1a1.dist-info/RECORD
